qiskit_aer/VERSION.txt
qiskit_aer/__init__.py
qiskit_aer/aererror.py
qiskit_aer/aerprovider.py
qiskit_aer/version.py
qiskit_aer/backends/__init__.py
qiskit_aer/backends/aer_compiler.py
qiskit_aer/backends/aer_simulator.py
qiskit_aer/backends/aerbackend.py
qiskit_aer/backends/backend_utils.py
qiskit_aer/backends/backendconfiguration.py
qiskit_aer/backends/backendproperties.py
qiskit_aer/backends/compatibility.py
qiskit_aer/backends/controller_wrappers.cp313-win32.pyd
qiskit_aer/backends/libopenblas.dll
qiskit_aer/backends/name_mapping.py
qiskit_aer/backends/qasm_simulator.py
qiskit_aer/backends/statevector_simulator.py
qiskit_aer/backends/unitary_simulator.py
qiskit_aer/jobs/__init__.py
qiskit_aer/jobs/aerjob.py
qiskit_aer/jobs/utils.py
qiskit_aer/library/__init__.py
qiskit_aer/library/default_qubits.py
qiskit_aer/library/instructions_table.csv
qiskit_aer/library/control_flow_instructions/__init__.py
qiskit_aer/library/control_flow_instructions/jump.py
qiskit_aer/library/control_flow_instructions/mark.py
qiskit_aer/library/control_flow_instructions/store.py
qiskit_aer/library/save_instructions/__init__.py
qiskit_aer/library/save_instructions/save_amplitudes.py
qiskit_aer/library/save_instructions/save_clifford.py
qiskit_aer/library/save_instructions/save_data.py
qiskit_aer/library/save_instructions/save_density_matrix.py
qiskit_aer/library/save_instructions/save_expectation_value.py
qiskit_aer/library/save_instructions/save_matrix_product_state.py
qiskit_aer/library/save_instructions/save_probabilities.py
qiskit_aer/library/save_instructions/save_stabilizer.py
qiskit_aer/library/save_instructions/save_state.py
qiskit_aer/library/save_instructions/save_statevector.py
qiskit_aer/library/save_instructions/save_superop.py
qiskit_aer/library/save_instructions/save_unitary.py
qiskit_aer/library/set_instructions/__init__.py
qiskit_aer/library/set_instructions/set_density_matrix.py
qiskit_aer/library/set_instructions/set_matrix_product_state.py
qiskit_aer-0.17.1.dist-info/licenses/LICENSE.txt
qiskit_aer-0.17.1.dist-info/METADATA
qiskit_aer-0.17.1.dist-info/WHEEL
qiskit_aer-0.17.1.dist-info/top_level.txt
qiskit_aer-0.17.1.dist-info/RECORD
