Metadata-Version: 2.4
Name: qiskit-aer
Version: 0.17.1
Summary: Aer - High performance simulators for Qiskit
Home-page: https://github.com/Qiskit/qiskit-aer
Author: AER Development Team
Author-email: qiskit@us.ibm.com
License: Apache 2.0
Keywords: qiskit,simulator,quantum computing,backend
Classifier: Environment :: Console
Classifier: License :: OSI Approved :: Apache Software License
Classifier: Intended Audience :: Developers
Classifier: Intended Audience :: Science/Research
Classifier: Operating System :: Microsoft :: Windows
Classifier: Operating System :: MacOS
Classifier: Operating System :: POSIX :: Linux
Classifier: Programming Language :: C++
Classifier: Programming Language :: Python :: 3 :: Only
Classifier: Programming Language :: Python :: 3.7
Classifier: Programming Language :: Python :: 3.8
Classifier: Programming Language :: Python :: 3.9
Classifier: Programming Language :: Python :: 3.10
Classifier: Programming Language :: Python :: 3.11
Classifier: Programming Language :: Python :: 3.12
Classifier: Topic :: Scientific/Engineering
Requires-Python: >=3.7
License-File: LICENSE.txt
Requires-Dist: qiskit>=1.1.0
Requires-Dist: numpy>=1.16.3
Requires-Dist: scipy>=1.0
Requires-Dist: psutil>=5
Requires-Dist: python-dateutil>=2.8.0
Dynamic: author
Dynamic: author-email
Dynamic: classifier
Dynamic: description
Dynamic: description-content-type
Dynamic: home-page
Dynamic: keywords
Dynamic: license
Dynamic: license-file
Dynamic: requires-dist
Dynamic: requires-python
Dynamic: summary
